.editorconfig
.gitignore
.gitlab-ci.yml
README.rst
publish.settings.sh
publish.sh
pyproject.toml
tsconfig.json
.idea/modules.xml
.idea/peek-plugin-livedb.iml
.idea/inspectionProfiles/Project_Default.xml
.idea/inspectionProfiles/profiles_settings.xml
peek_plugin_livedb/__init__.py
peek_plugin_livedb/plugin_package.json
peek_plugin_livedb.egg-info/PKG-INFO
peek_plugin_livedb.egg-info/SOURCES.txt
peek_plugin_livedb.egg-info/dependency_links.txt
peek_plugin_livedb.egg-info/requires.txt
peek_plugin_livedb.egg-info/top_level.txt
peek_plugin_livedb/_private/PluginNames.py
peek_plugin_livedb/_private/__init__.py
peek_plugin_livedb/_private/alembic.ini
peek_plugin_livedb/_private/admin-app/livedb.module.ts
peek_plugin_livedb/_private/admin-app/components/edit-setting-table/edit.component.html
peek_plugin_livedb/_private/admin-app/components/edit-setting-table/edit.component.scss
peek_plugin_livedb/_private/admin-app/components/edit-setting-table/edit.component.ts
peek_plugin_livedb/_private/admin-app/components/livedb-page/livedb-page.component.html
peek_plugin_livedb/_private/admin-app/components/livedb-page/livedb-page.component.scss
peek_plugin_livedb/_private/admin-app/components/livedb-page/livedb-page.component.ts
peek_plugin_livedb/_private/admin-app/components/status/status.component.html
peek_plugin_livedb/_private/admin-app/components/status/status.component.scss
peek_plugin_livedb/_private/admin-app/components/status/status.component.ts
peek_plugin_livedb/_private/admin-app/tuples/AdminStatusTuple.ts
peek_plugin_livedb/_private/agent/AgentEntryHook.py
peek_plugin_livedb/_private/agent/__init__.py
peek_plugin_livedb/_private/alembic/__init__.py
peek_plugin_livedb/_private/alembic/env.py
peek_plugin_livedb/_private/alembic/script.py.mako
peek_plugin_livedb/_private/alembic/versions/19b2a8d326ad_removed_string_lengths.py
peek_plugin_livedb/_private/alembic/versions/1f014c013f8b_fixed_nullable_queue_rawvalue.py
peek_plugin_livedb/_private/alembic/versions/64309a77b48d_initial.py
peek_plugin_livedb/_private/alembic/versions/__init__.py
peek_plugin_livedb/_private/alembic/versions/ab9da4532175_fixed_key_modelset_index.py
