Metadata-Version: 2.4
Name: peek-plugin-livedb
Version: 5.0.4
Summary: Peek Plugin LiveDB - storage of live values from schematics
Author-email: Synerty <contact@synerty.com>
Project-URL: Homepage, https://github.com/Synerty/peek-plugin-livedb
Keywords: Peek,Python,Platform,synerty
Requires-Dist: peek-plugin-base==5.0.4
